frequency/adapter/__init__.py
frequency/adapter/base.py
frequency/adapter/util.py
frequency/api/v1/server/dependencies.py
frequency/api/v1/server/main.py
frequency/api/v1/server/models.py
frequency/api/v1/server/routers/adapter.py
frequency/api/v1/server/routers/base.py
frequency/api/v1/server/routers/model.py
frequency/api/v1/server.yaml
frequency/client/__init__.py
frequency/client/client.py
frequency/client/v1/frequency_api/__init__.py
frequency/client/v1/frequency_api/_client.py
frequency/client/v1/frequency_api/_configuration.py
frequency/client/v1/frequency_api/_operations/__init__.py
frequency/client/v1/frequency_api/_operations/_operations.py
frequency/client/v1/frequency_api/_operations/_patch.py
frequency/client/v1/frequency_api/_patch.py
frequency/client/v1/frequency_api/_serialization.py
frequency/client/v1/frequency_api/_vendor.py
frequency/client/v1/frequency_api/aio/__init__.py
frequency/client/v1/frequency_api/aio/_client.py
frequency/client/v1/frequency_api/aio/_configuration.py
frequency/client/v1/frequency_api/aio/_operations/__init__.py
frequency/client/v1/frequency_api/aio/_operations/_operations.py
frequency/client/v1/frequency_api/aio/_operations/_patch.py
frequency/client/v1/frequency_api/aio/_patch.py
frequency/client/v1/frequency_api/aio/_vendor.py
frequency/client/v1/frequency_api/py.typed
frequency/db/conn.py
frequency/db/models.py
frequency/model/__init__.py
frequency/model/base.py
frequency/provider/base.py
frequency/provider/runpod.py
frequency/server/dependencies.py
frequency/server/main.py
frequency/server/routers/adapter.py
frequency/server/routers/base.py
frequency/server/routers/model.py
frequency_ai-0.1.8.dist-info/LICENSE
frequency_ai-0.1.8.dist-info/METADATA
frequency_ai-0.1.8.dist-info/WHEEL
frequency_ai-0.1.8.dist-info/RECORD
