Metadata-Version: 2.1
Name: frequency-ai
Version: 0.1.8
Summary: Effiently serve LoRA tuned models
License: Apache 2.0
Author: Patrick Barker
Author-email: patrickbarkerco@gmail.com
Requires-Python: >=3.10,<4.0
Classifier: License :: Other/Proprietary License
Classifier: Programming Language :: Python :: 3
Classifier: Programming Language :: Python :: 3.10
Classifier: Programming Language :: Python :: 3.11
Requires-Dist: azure-core (>=1.29.6,<2.0.0)
Requires-Dist: einops (>=0.7.0,<0.8.0)
Requires-Dist: fastapi (>=0.109.0,<0.110.0)
Requires-Dist: ipykernel (>=6.28.0,<7.0.0)
Requires-Dist: isodate (>=0.6.1,<0.7.0)
Requires-Dist: pillow (>=10.2.0,<11.0.0)
Requires-Dist: sqlalchemy (>=2.0.25,<3.0.0)
Requires-Dist: torchvision (>=0.16.2,<0.17.0)
Requires-Dist: transformers-stream-generator (>=0.0.4,<0.0.5)
Requires-Dist: uvicorn (>=0.25.0,<0.26.0)
